aCrypt/__init__.py
aCrypt-0.1.7.dist-info/LICENSE
aCrypt-0.1.7.dist-info/METADATA
aCrypt-0.1.7.dist-info/WHEEL
aCrypt-0.1.7.dist-info/top_level.txt
aCrypt-0.1.7.dist-info/RECORD
