Metadata-Version: 2.1
Name: aCrypt
Version: 0.1.7
Summary: Ciphering made easy.
Home-page: https://repl.it/@ChezCoder/aCrypt
Author: ChezCoder
Author-email: mrpizzaguyytb@gmail.com
License: UNKNOWN
Platform: UNKNOWN
Classifier: Programming Language :: Python :: 2
Classifier: License :: OSI Approved :: MIT License
Classifier: Operating System :: OS Independent
Requires-Python: >=2.7
